daflip/__init__.py
daflip/cli.py
daflip/config.py
daflip/controllers.py
daflip/models.py
daflip/py.typed
daflip/services.py
daflip/utils.py
daflip-0.1.10.dist-info/licenses/LICENSE
daflip-0.1.10.dist-info/METADATA
daflip-0.1.10.dist-info/WHEEL
daflip-0.1.10.dist-info/entry_points.txt
daflip-0.1.10.dist-info/top_level.txt
daflip-0.1.10.dist-info/RECORD
