Metadata-Version: 2.4
Name: daflip
Version: 0.1.10
Summary: A modern Python CLI tool for converting data files between formats.
Author-email: Vincent Grégoire <vincent.gregoire@gmail.com>
License-Expression: MIT
Requires-Python: >=3.9
License-File: LICENSE
Requires-Dist: openpyxl>=3.1.5
Requires-Dist: pandas>=2.3.0
Requires-Dist: pyarrow>=20.0.0
Requires-Dist: python-dotenv>=1.1.0
Requires-Dist: rich>=14.0.0
Requires-Dist: typer>=0.16.0
Requires-Dist: xlrd>=2.0.2
Requires-Dist: xlsxwriter>=3.2.5
Dynamic: license-file
